[{"id":1,"first_name":"Hayes","last_name":"Whelpdale","email":"hwhelpdale0@huffingtonpost.com","gender":"M"},
{"id":2,"first_name":"Corabella","last_name":"Sherington","email":"csherington1@tripadvisor.com","gender":"F"},
{"id":3,"first_name":"Betsey","last_name":"Seyfart","email":"bseyfart2@xing.com","gender":"F"},
{"id":4,"first_name":"Isacco","last_name":"Meekins","email":"imeekins3@webs.com","gender":"M"},
{"id":5,"first_name":"Ddene","last_name":"Stife","email":"dstife4@disqus.com","gender":"F"},
{"id":6,"first_name":"Giselbert","last_name":"Moores","email":"gmoores5@rambler.ru","gender":"M"},
{"id":7,"first_name":"Gun","last_name":"Coggell","email":"gcoggell6@twitpic.com","gender":"M"},
{"id":8,"first_name":"Parke","last_name":"Morde","email":"pmorde7@go.com","gender":"M"},
{"id":9,"first_name":"Daryle","last_name":"Paybody","email":"dpaybody8@dedecms.com","gender":"M"},
{"id":10,"first_name":"Griffith","last_name":"Sail","email":"gsail9@eventbrite.com","gender":"M"},
{"id":11,"first_name":"Piggy","last_name":"Lattos","email":"plattosa@ebay.com","gender":"M"},
{"id":12,"first_name":"Bobbye","last_name":"Samwaye","email":"bsamwayeb@yelp.com","gender":"F"},
{"id":13,"first_name":"Armand","last_name":"Vaan","email":"avaanc@scribd.com","gender":"M"},
{"id":14,"first_name":"Mercie","last_name":"Egger","email":"meggerd@aol.com","gender":"F"},
{"id":15,"first_name":"Ali","last_name":"Kierans","email":"akieranse@diigo.com","gender":"F"},
{"id":16,"first_name":"Michaella","last_name":"Mintoff","email":"mmintofff@pagesperso-orange.fr","gender":"F"},
{"id":17,"first_name":"Fulton","last_name":"Odde","email":"foddeg@auda.org.au","gender":"M"},
{"id":18,"first_name":"Frannie","last_name":"Byfford","email":"fbyffordh@opensource.org","gender":"M"},
{"id":19,"first_name":"Sergei","last_name":"Gullivent","email":"sgulliventi@vkontakte.ru","gender":"M"},
{"id":20,"first_name":"Koressa","last_name":"Antonias","email":"kantoniasj@yale.edu","gender":"F"},
{"id":21,"first_name":"Junina","last_name":"Radolf","email":"jradolfk@nytimes.com","gender":"F"},
{"id":22,"first_name":"Margarette","last_name":"Wilcockes","email":"mwilcockesl@ihg.com","gender":"F"},
{"id":23,"first_name":"Connie","last_name":"Menendez","email":"cmenendezm@globo.com","gender":"M"},
{"id":24,"first_name":"Tamarra","last_name":"Malins","email":"tmalinsn@shutterfly.com","gender":"F"},
{"id":25,"first_name":"Nollie","last_name":"Powley","email":"npowleyo@zimbio.com","gender":"M"},
{"id":26,"first_name":"Marlyn","last_name":"Mebius","email":"mmebiusp@webs.com","gender":"F"},
{"id":27,"first_name":"Elton","last_name":"Morlon","email":"emorlonq@mozilla.org","gender":"M"},
{"id":28,"first_name":"Kaspar","last_name":"Munks","email":"kmunksr@mapquest.com","gender":"M"},
{"id":29,"first_name":"Bibbye","last_name":"Robertot","email":"brobertots@state.gov","gender":"F"},
{"id":30,"first_name":"Odey","last_name":"Simonnin","email":"osimonnint@google.pl","gender":"M"},
{"id":31,"first_name":"Sigfrid","last_name":"Glaister","email":"sglaisteru@narod.ru","gender":"M"},
{"id":32,"first_name":"Derry","last_name":"Shelliday","email":"dshellidayv@aboutads.info","gender":"M"},
{"id":33,"first_name":"Daisy","last_name":"Andryushchenko","email":"dandryushchenkow@ibm.com","gender":"F"},
{"id":34,"first_name":"Fax","last_name":"Cooke","email":"fcookex@nydailynews.com","gender":"M"},
{"id":35,"first_name":"Gabi","last_name":"Pelerin","email":"gpeleriny@omniture.com","gender":"F"},
{"id":36,"first_name":"Lawrence","last_name":"Maile","email":"lmailez@reuters.com","gender":"M"},
{"id":37,"first_name":"Catriona","last_name":"Bernocchi","email":"cbernocchi10@omniture.com","gender":"F"},
{"id":38,"first_name":"Reynolds","last_name":"Philippault","email":"rphilippault11@wisc.edu","gender":"M"},
{"id":39,"first_name":"Dalton","last_name":"Kiledal","email":"dkiledal12@webs.com","gender":"M"},
{"id":40,"first_name":"Antonio","last_name":"Copcote","email":"acopcote13@mac.com","gender":"M"},
{"id":41,"first_name":"Ninon","last_name":"Rosnau","email":"nrosnau14@123-reg.co.uk","gender":"F"},
{"id":42,"first_name":"Lazarus","last_name":"Roistone","email":"lroistone15@adobe.com","gender":"M"},
{"id":43,"first_name":"Major","last_name":"Oldmeadow","email":"moldmeadow16@macromedia.com","gender":"M"},
{"id":44,"first_name":"Ernie","last_name":"Salomon","email":"esalomon17@prnewswire.com","gender":"M"},
{"id":45,"first_name":"Kerry","last_name":"Heddy","email":"kheddy18@last.fm","gender":"M"},
{"id":46,"first_name":"Prue","last_name":"Della","email":"pdella19@edublogs.org","gender":"F"},
{"id":47,"first_name":"Jaimie","last_name":"Lynde","email":"jlynde1a@go.com","gender":"F"},
{"id":48,"first_name":"Bess","last_name":"McTrustam","email":"bmctrustam1b@economist.com","gender":"F"},
{"id":49,"first_name":"Sergent","last_name":"Nason","email":"snason1c@omniture.com","gender":"M"},
{"id":50,"first_name":"Dagmar","last_name":"Digweed","email":"ddigweed1d@ow.ly","gender":"F"},
{"id":51,"first_name":"Harold","last_name":"Fridlington","email":"hfridlington1e@fda.gov","gender":"M"},
{"id":52,"first_name":"Therese","last_name":"Sholl","email":"tsholl1f@123-reg.co.uk","gender":"F"},
{"id":53,"first_name":"Jasper","last_name":"Feechum","email":"jfeechum1g@aboutads.info","gender":"M"},
{"id":54,"first_name":"Torry","last_name":"Loraine","email":"tloraine1h@reuters.com","gender":"M"},
{"id":55,"first_name":"Janie","last_name":"Flaune","email":"jflaune1i@engadget.com","gender":"F"},
{"id":56,"first_name":"Harley","last_name":"McTerlagh","email":"hmcterlagh1j@weibo.com","gender":"M"},
{"id":57,"first_name":"Coriss","last_name":"Bercevelo","email":"cbercevelo1k@google.com","gender":"F"},
{"id":58,"first_name":"Bentlee","last_name":"Huriche","email":"bhuriche1l@miitbeian.gov.cn","gender":"M"},
{"id":59,"first_name":"Elinor","last_name":"Grimwade","email":"egrimwade1m@mlb.com","gender":"F"},
{"id":60,"first_name":"Lynnell","last_name":"MacBean","email":"lmacbean1n@jiathis.com","gender":"F"},
{"id":61,"first_name":"Lorene","last_name":"Cantillon","email":"lcantillon1o@microsoft.com","gender":"F"},
{"id":62,"first_name":"Vic","last_name":"Gurry","email":"vgurry1p@indiegogo.com","gender":"M"},
{"id":63,"first_name":"Bernarr","last_name":"Gribbell","email":"bgribbell1q@livejournal.com","gender":"M"},
{"id":64,"first_name":"Elonore","last_name":"Tenant","email":"etenant1r@weebly.com","gender":"F"},
{"id":65,"first_name":"Halie","last_name":"Mundle","email":"hmundle1s@paypal.com","gender":"F"},
{"id":66,"first_name":"Francisca","last_name":"Moulding","email":"fmoulding1t@archive.org","gender":"F"},
{"id":67,"first_name":"Merell","last_name":"Jobling","email":"mjobling1u@china.com.cn","gender":"M"},
{"id":68,"first_name":"Marge","last_name":"Unstead","email":"munstead1v@phoca.cz","gender":"F"},
{"id":69,"first_name":"Worthy","last_name":"Scotchmer","email":"wscotchmer1w@vimeo.com","gender":"M"},
{"id":70,"first_name":"Arly","last_name":"Quinby","email":"aquinby1x@arizona.edu","gender":"F"},
{"id":71,"first_name":"Nealon","last_name":"Cullin","email":"ncullin1y@miibeian.gov.cn","gender":"M"},
{"id":72,"first_name":"Dorrie","last_name":"Slimmon","email":"dslimmon1z@businesswire.com","gender":"F"},
{"id":73,"first_name":"Trip","last_name":"Scorey","email":"tscorey20@twitter.com","gender":"M"},
{"id":74,"first_name":"Marice","last_name":"Stanton","email":"mstanton21@hp.com","gender":"F"},
{"id":75,"first_name":"Wayne","last_name":"Luppitt","email":"wluppitt22@blogs.com","gender":"M"},
{"id":76,"first_name":"Dredi","last_name":"Shelliday","email":"dshelliday23@1688.com","gender":"F"},
{"id":77,"first_name":"Vally","last_name":"Welton","email":"vwelton24@cisco.com","gender":"F"},
{"id":78,"first_name":"Stanly","last_name":"McKennan","email":"smckennan25@cloudflare.com","gender":"M"},
{"id":79,"first_name":"Bathsheba","last_name":"Swindlehurst","email":"bswindlehurst26@weebly.com","gender":"F"},
{"id":80,"first_name":"Kora","last_name":"Hardin","email":"khardin27@a8.net","gender":"F"},
{"id":81,"first_name":"Fanchette","last_name":"Brayshay","email":"fbrayshay28@4shared.com","gender":"F"},
{"id":82,"first_name":"Hermon","last_name":"Kemm","email":"hkemm29@java.com","gender":"M"},
{"id":83,"first_name":"Kristy","last_name":"Goulding","email":"kgoulding2a@scribd.com","gender":"F"},
{"id":84,"first_name":"Albina","last_name":"Saice","email":"asaice2b@last.fm","gender":"F"},
{"id":85,"first_name":"Roxane","last_name":"Edler","email":"redler2c@dailymail.co.uk","gender":"F"},
{"id":86,"first_name":"Jessalin","last_name":"Chatain","email":"jchatain2d@java.com","gender":"F"},
{"id":87,"first_name":"Manya","last_name":"Pinkney","email":"mpinkney2e@friendfeed.com","gender":"F"},
{"id":88,"first_name":"Gerrard","last_name":"Littlewood","email":"glittlewood2f@omniture.com","gender":"M"},
{"id":89,"first_name":"Kim","last_name":"Dingle","email":"kdingle2g@clickbank.net","gender":"M"},
{"id":90,"first_name":"Vania","last_name":"Kondratovich","email":"vkondratovich2h@engadget.com","gender":"F"},
{"id":91,"first_name":"Hilarius","last_name":"Fawcitt","email":"hfawcitt2i@nature.com","gender":"M"},
{"id":92,"first_name":"Bobbie","last_name":"Dobbing","email":"bdobbing2j@patch.com","gender":"M"},
{"id":93,"first_name":"Leo","last_name":"Kirvell","email":"lkirvell2k@ibm.com","gender":"M"},
{"id":94,"first_name":"Conney","last_name":"Cockburn","email":"ccockburn2l@soup.io","gender":"M"},
{"id":95,"first_name":"Denney","last_name":"Jaquemar","email":"djaquemar2m@google.es","gender":"M"},
{"id":96,"first_name":"Shane","last_name":"Humbert","email":"shumbert2n@behance.net","gender":"F"},
{"id":97,"first_name":"Dirk","last_name":"Hatliff","email":"dhatliff2o@wordpress.org","gender":"M"},
{"id":98,"first_name":"Tyne","last_name":"Wedmore.","email":"twedmore2p@geocities.com","gender":"F"},
{"id":99,"first_name":"Tyrone","last_name":"Shorton","email":"tshorton2q@pinterest.com","gender":"M"},
{"id":100,"first_name":"Tadd","last_name":"Scopes","email":"tscopes2r@princeton.edu","gender":"M"}]